carate/__init__.py
carate/default_interface.py
carate/default_interface.pyi
carate/main.py
carate/cli/__init__.py
carate/cli/automate.py
carate/cli/automate.pyi
carate/config_adapter/__init__.py
carate/config_adapter/config.py
carate/config_adapter/config.pyi
carate/evaluation/__init__.py
carate/evaluation/base.py
carate/evaluation/base.pyi
carate/evaluation/classification.py
carate/evaluation/classification.pyi
carate/evaluation/classification_whole_dataset.py
carate/evaluation/regression.py
carate/evaluation/regression.pyi
carate/evaluation/regression_custom_loss.py
carate/loader/__init__.py
carate/loader/load_data.py
carate/loader/load_data.pyi
carate/logging/__init__.py
carate/logging/metrics_logger.py
carate/models/__init__.py
carate/models/base_model.py
carate/models/base_model.pyi
carate/models/c_classification.py
carate/models/c_plain_classification.py
carate/models/c_plain_regression.py
carate/models/c_regression.py
carate/models/cc_classification.py
carate/models/cc_regression.py
carate/models/cg_without_linear_block_classification.py
carate/models/cg_without_linear_block_regression.py
carate/models/cgc_classification.py
carate/models/cgc_classification.pyi
carate/models/cgc_classification_jax.py
carate/models/cgc_regression.py
carate/models/cgc_regression.pyi
carate/models/cgc_regression_jax.py
carate/models/cgc_without_linear_block_classification.py
carate/models/cgc_without_linear_block_regression.py
carate/models/g_classification.py
carate/models/g_regression.py
carate/models/gatv2_classification.py
carate/models/gatv2_regression.py
carate/models/gcc_classification.py
carate/models/gcc_regression.py
carate/models/graph_transformer_classification.py
carate/models/graph_transformer_regression.py
carate/models/linear_block_classification.py
carate/models/linear_block_classification_pooling.py
carate/models/linear_block_regression.py
carate/models/linear_block_regression_pooling.py
carate/models/models.pyi
carate/optimizer/__init__.py
carate-0.3.32.dist-info/licenses/LICENSE
carate-0.3.32.dist-info/METADATA
carate-0.3.32.dist-info/WHEEL
carate-0.3.32.dist-info/entry_points.txt
carate-0.3.32.dist-info/top_level.txt
carate-0.3.32.dist-info/RECORD
