Metadata-Version: 2.4
Name: carate
Version: 0.3.32
Summary: Chemical and Pharmaceutical Autoencoder - Providing reproducible modelling for quantum chemistry
Author-email: "Julian M. Kleber" <julian.m.kleber@gmail.com>
Project-URL: Homepage, https://www.codeberg.org/sail.black/carate.git
Project-URL: Bug Tracker, https://www.codeberg.org/sail.black/carate.git/issues
Classifier: Programming Language :: Python :: 3
Classifier: License :: OSI Approved :: GNU General Public License v3 or later (GPLv3+)
Classifier: Operating System :: OS Independent
Requires-Python: >=3.8
License-File: LICENSE
Requires-Dist: torch==1.13.1
Requires-Dist: torch-sparse-carate
Requires-Dist: torch-scatter-carate
Requires-Dist: torch-geometric
Requires-Dist: rdkit-pypi
Requires-Dist: networkx[default]
Requires-Dist: matplotlib
Requires-Dist: Click
Requires-Dist: amarium
Requires-Dist: black
Requires-Dist: numpy<2
Requires-Dist: scikit-learn
Requires-Dist: applique
Dynamic: license-file
